thirteen_calendar/__init__.py
thirteen_calendar-0.1.0.dist-info/METADATA
thirteen_calendar-0.1.0.dist-info/WHEEL
thirteen_calendar-0.1.0.dist-info/top_level.txt
thirteen_calendar-0.1.0.dist-info/RECORD
