Metadata-Version: 2.4
Name: thirteen_calendar
Version: 0.1.0
Summary: A custom calendar and clock system with 13 months, 26 hours, and astronomical calculations.
Author: Gemini
Classifier: Programming Language :: Python :: 3
Classifier: License :: OSI Approved :: MIT License
Classifier: Operating System :: OS Independent
Requires-Python: >=3.6
Dynamic: author
Dynamic: classifier
Dynamic: requires-python
Dynamic: summary
